MANIFEST.in
README.md
setup.py
chassis/__init__.py
chassis.egg-info/PKG-INFO
chassis.egg-info/SOURCES.txt
chassis.egg-info/dependency_links.txt
chassis.egg-info/pbr.json
chassis.egg-info/requires.txt
chassis.egg-info/top_level.txt
chassis/models/__init__.py
chassis/services/__init__.py
chassis/services/cache.py
chassis/services/data_context.py
chassis/services/dependency_injection/__init__.py
chassis/services/dependency_injection/resolver.py
chassis/test/__init__.py
chassis/test/example_classes.py
chassis/test/services/__init__.py
chassis/test/services/cache_test.py
chassis/test/services/data_context_test.py
chassis/test/services/dependency_injection/__init__.py
chassis/test/services/dependency_injection/resolver_test.py
chassis/test/util/__init__.py
chassis/test/util/decorators_test.py
chassis/test/util/encoders_test.py
chassis/test/util/params_test.py
chassis/test/util/validators_test.py
chassis/tools/__init__.py
chassis/tools/lint.py
chassis/util/__init__.py
chassis/util/decorators.py
chassis/util/encoders.py
chassis/util/params.py
chassis/util/tree.py
chassis/util/validators.py
chassis/web/__init__.py