Metadata-Version: 1.1
Name: chassis
Version: 0.1.6
Summary: Opinionated REST Framework
Home-page: https://github.com/refinery29/chassis
Author: Refinery 29
Author-email: chassis-project@refinery29.com
License: UNKNOWN
Download-URL: https://github.com/refinery29/chassis/archive/v0.1.6.tar.gz
Keywords: Tornado,RESTful,REST,API,JSON,framework
Platform: UNKNOWN
Classifier: Development Status :: 3 - Alpha
Classifier: Environment :: Web Environment
Classifier: License :: OSI Approved :: MIT License
Classifier: Intended Audience :: Developers
Classifier: Programming Language :: Python
Classifier: Programming Language :: Python :: 2
Classifier: Programming Language :: Python :: 2.6
Classifier: Programming Language :: Python :: 2.7
Classifier: Programming Language :: Python :: 3
Classifier: Programming Language :: Python :: 3.2
Classifier: Programming Language :: Python :: 3.3
Classifier: Programming Language :: Python :: 3.4
Classifier: Topic :: Internet :: WWW/HTTP
Classifier: Topic :: Internet :: WWW/HTTP :: Dynamic Content
Classifier: Topic :: Internet :: WWW/HTTP :: HTTP Servers
Classifier: Topic :: Software Development :: Libraries :: Application Frameworks
